hamilton/__init__.py
hamilton/ad_hoc_utils.py
hamilton/async_driver.py
hamilton/base.py
hamilton/driver.py
hamilton/function_modifiers_base.py
hamilton/graph.py
hamilton/graph_types.py
hamilton/graph_utils.py
hamilton/htypes.py
hamilton/log_setup.py
hamilton/models.py
hamilton/node.py
hamilton/registry.py
hamilton/settings.py
hamilton/telemetry.py
hamilton/version.py
hamilton/caching/__init__.py
hamilton/caching/adapter.py
hamilton/caching/cache_key.py
hamilton/caching/fingerprinting.py
hamilton/caching/stores/__init__.py
hamilton/caching/stores/base.py
hamilton/caching/stores/file.py
hamilton/caching/stores/memory.py
hamilton/caching/stores/sqlite.py
hamilton/caching/stores/utils.py
hamilton/cli/__init__.py
hamilton/cli/__main__.py
hamilton/cli/commands.py
hamilton/cli/logic.py
hamilton/common/__init__.py
hamilton/contrib/__init__.py
hamilton/data_quality/__init__.py
hamilton/data_quality/base.py
hamilton/data_quality/default_validators.py
hamilton/data_quality/pandera_validators.py
hamilton/dataflows/__init__.py
hamilton/dataflows/template/README.md
hamilton/dataflows/template/__init__.py
hamilton/dataflows/template/author.md
hamilton/dataflows/template/requirements.txt
hamilton/dataflows/template/tags.json
hamilton/dataflows/template/valid_configs.jsonl
hamilton/dev_utils/__init__.py
hamilton/dev_utils/deprecation.py
hamilton/execution/__init__.py
hamilton/execution/debugging_utils.py
hamilton/execution/executors.py
hamilton/execution/graph_functions.py
hamilton/execution/grouping.py
hamilton/execution/state.py
hamilton/experimental/__init__.py
hamilton/experimental/databackend.py
hamilton/experimental/h_async.py
hamilton/experimental/h_cache.py
hamilton/experimental/h_dask.py
hamilton/experimental/h_databackends.py
hamilton/experimental/h_ray.py
hamilton/experimental/h_spark.py
hamilton/experimental/decorators/__init__.py
hamilton/experimental/decorators/parameterize_frame.py
hamilton/function_modifiers/README
hamilton/function_modifiers/__init__.py
sf_hamilton-1.89.0.dist-info/entry_points.txt
sf_hamilton-1.89.0.dist-info/licenses/LICENSE
sf_hamilton-1.89.0.dist-info/WHEEL
sf_hamilton-1.89.0.dist-info/METADATA
sf_hamilton-1.89.0.dist-info/RECORD
