Metadata-Version: 2.4
Name: sf-hamilton
Version: 1.89.0
Summary: Hamilton, the micro-framework for creating dataframes.
Keywords: hamilton
Author-email: Stefan Krawczyk <stefank@cs.stanford.edu>, Elijah ben Izzy <elijah@dagworks.io>
Requires-Python: >=3.8.1, <4
Classifier: Development Status :: 5 - Production/Stable
Classifier: Intended Audience :: Developers
Classifier: Natural Language :: English
Classifier: License :: OSI Approved :: Apache Software License
Classifier: Programming Language :: Python :: 3
Classifier: Programming Language :: Python :: 3.8
Classifier: Programming Language :: Python :: 3.9
Classifier: Programming Language :: Python :: 3.10
Classifier: Programming Language :: Python :: 3.11
Classifier: Programming Language :: Python :: 3.12
License-File: LICENSE
Requires-Dist: numpy
Requires-Dist: pandas
Requires-Dist: typing_extensions > 4.0.0
Requires-Dist: typing_inspect
Requires-Dist: typer ; extra == "cli"
Requires-Dist: dask[complete] ; extra == "dask"
Requires-Dist: dask[array] ; extra == "dask-array"
Requires-Dist: dask[dataframe] ; extra == "dask-dataframe"
Requires-Dist: dask[diagnostics] ; extra == "dask-diagnostics"
Requires-Dist: dask[distributed] ; extra == "dask-distributed"
Requires-Dist: ddtrace<3.0 ; extra == "datadog"
Requires-Dist: diskcache ; extra == "diskcache"
Requires-Dist: fastapi ; extra == "experiments"
Requires-Dist: fastui ; extra == "experiments"
Requires-Dist: uvicorn ; extra == "experiments"
Requires-Dist: sf-hamilton-lsp ; extra == "lsp"
Requires-Dist: openlineage-python ; extra == "openlineage"
Requires-Dist: pandera ; extra == "pandera"
Requires-Dist: pydantic>=2.0 ; extra == "pydantic"
Requires-Dist: pyspark[pandas-on-spark, sql] ; extra == "pyspark"
Requires-Dist: ray>=2.0.0 ; extra == "ray"
Requires-Dist: pyarrow ; extra == "ray"
Requires-Dist: rich ; extra == "rich"
Requires-Dist: sf-hamilton-sdk ; extra == "sdk"
Requires-Dist: slack-sdk ; extra == "slack"
Requires-Dist: tqdm ; extra == "tqdm"
Requires-Dist: sf-hamilton-ui ; extra == "ui"
Requires-Dist: vaex ; extra == "vaex" and ( python_version <= '3.10')
Requires-Dist: graphviz ; extra == "visualization"
Requires-Dist: networkx ; extra == "visualization"
Project-URL: changelog, https://github.com/apache/hamilton/releases
Project-URL: documentation, https://hamilton.apache.org/en/latest/
Project-URL: homepage, https://www.tryhamilton.dev/
Project-URL: issues, https://github.com/apache/hamilton/issues
Project-URL: slack, https://join.slack.com/t/hamilton-opensource/shared_invite/zt-2niepkra8-DGKGf_tTYhXuJWBTXtIs4g
Project-URL: source, https://github.com/apache/hamilton
Provides-Extra: cli
Provides-Extra: dask
Provides-Extra: dask-array
Provides-Extra: dask-dataframe
Provides-Extra: dask-diagnostics
Provides-Extra: dask-distributed
Provides-Extra: datadog
Provides-Extra: diskcache
Provides-Extra: experiments
Provides-Extra: lsp
Provides-Extra: openlineage
Provides-Extra: pandera
Provides-Extra: pydantic
Provides-Extra: pyspark
Provides-Extra: ray
Provides-Extra: rich
Provides-Extra: sdk
Provides-Extra: slack
Provides-Extra: tqdm
Provides-Extra: ui
Provides-Extra: vaex
Provides-Extra: visualization
